superneuroabm/__init__.py
superneuroabm/model.py
superneuroabm/neuron.py
superneuroabm/core/__init__.py
superneuroabm/core/agent.py
superneuroabm/core/model.py
superneuroabm/core/util.py
SuperNeuroABM-0.3.0.dist-info/LICENSE
SuperNeuroABM-0.3.0.dist-info/METADATA
SuperNeuroABM-0.3.0.dist-info/WHEEL
SuperNeuroABM-0.3.0.dist-info/top_level.txt
SuperNeuroABM-0.3.0.dist-info/RECORD
