Metadata-Version: 2.1
Name: SuperNeuroABM
Version: 0.3.0
Summary: A GPU-based multi-agent simulation framework for neuromorphic computing.
Home-page: https://code.ornl.gov/superneuro/superneuroabm
Author: Chathika Gunaratne, Prasanna Date, Shruti Kulkarni, Xi Zhang
Author-email: gunaratnecs@ornl.gov
License: GPL
Project-URL: Source, https://github.com/ORNL/superneuroabm
License-File: LICENSE
Requires-Dist: numba (==0.55.1)
Requires-Dist: numpy (==1.21.6)
Requires-Dist: tqdm (==4.64.1)
